dabl/__init__.py
dabl/_available_if.py
dabl/_config.py
dabl/_resample.py
dabl/explain.py
dabl/models.py
dabl/pipelines.py
dabl/preprocessing.py
dabl/search.py
dabl/utils.py
dabl/datasets/__init__.py
dabl/datasets/adult.csv.gz
dabl/datasets/ames_housing.pkl.bz2
dabl/datasets/titanic.csv
dabl/plot/__init__.py
dabl/plot/sankey.py
dabl/plot/supervised.py
dabl/plot/utils.py
dabl/portfolios/__init__.py
dabl/portfolios/portfolio_base.py
dabl/portfolios/portfolio_hgb.py
dabl/portfolios/portfolio_lr.py
dabl/portfolios/portfolio_mixed.py
dabl/portfolios/portfolio_rf.py
dabl/portfolios/portfolio_svc.py
dabl-0.3.2.dist-info/LICENSE
dabl-0.3.2.dist-info/METADATA
dabl-0.3.2.dist-info/WHEEL
dabl-0.3.2.dist-info/top_level.txt
dabl-0.3.2.dist-info/RECORD
