Metadata-Version: 2.1
Name: dabl
Version: 0.3.2
Summary: Data Analysis Baseline Library
Author-email: Andreas Mueller <t3kcit+githubspam@gmail.com>
Maintainer-email: Andreas Mueller <t3kcit+githubspam@gmail.com>, Brian Kroth <bpkroth+githubspam@gmail.com>
License: Copyright (c) 2016, Vighnesh Birodkar
Project-URL: Documentation, https://dabl.github.io/
Project-URL: Repository, https://github.com/dabl/dabl
Project-URL: Issues, https://github.com/dabl/dabl/issues
Keywords: data analysis,visualization
Classifier: Intended Audience :: Developers
Classifier: Intended Audience :: Science/Research
Classifier: License :: OSI Approved :: BSD License
Classifier: Operating System :: OS Independent
Classifier: Programming Language :: Python :: 3
Classifier: Programming Language :: Python :: 3.8
Classifier: Programming Language :: Python :: 3.9
Classifier: Programming Language :: Python :: 3.10
Classifier: Programming Language :: Python :: 3.11
Classifier: Programming Language :: Python :: 3.12
Classifier: Topic :: Scientific/Engineering :: Information Analysis
Classifier: Topic :: Scientific/Engineering :: Visualization
Requires-Python: >=3.8
License-File: LICENSE
Requires-Dist: packaging
Requires-Dist: numpy
Requires-Dist: scipy
Requires-Dist: scikit-learn>=1.1
Requires-Dist: numpy<2.0; python_version < "3.9"
Requires-Dist: scikit-learn<1.4; python_version < "3.9"
Requires-Dist: scikit-learn>=1.3; python_version >= "3.9"
Requires-Dist: pandas
Requires-Dist: matplotlib<3.8; python_version < "3.9"
Requires-Dist: matplotlib>=3.8; python_version >= "3.9"
Requires-Dist: seaborn
